pydataapi_postgres/__init__.py
pydataapi_postgres/dbapi.py
pydataapi_postgres/dialect.py
pydataapi_postgres/exceptions.py
pydataapi_postgres/pydataapi.py
pydataapi_postgres/version.py
pydataapipostgres/__init__.py
pydataapipostgres/dbapi.py
pydataapipostgres/dialect.py
pydataapipostgres/exceptions.py
pydataapipostgres/pydataapi.py
pydataapipostgres/pydataapipostgres.py
pydataapipostgres/version.py
pydataapi_postgres-0.1.3.dist-info/LICENSE
pydataapi_postgres-0.1.3.dist-info/METADATA
pydataapi_postgres-0.1.3.dist-info/WHEEL
pydataapi_postgres-0.1.3.dist-info/entry_points.txt
pydataapi_postgres-0.1.3.dist-info/top_level.txt
pydataapi_postgres-0.1.3.dist-info/zip-safe
pydataapi_postgres-0.1.3.dist-info/RECORD
