Metadata-Version: 2.1
Name: pydataapi-postgres
Version: 0.1.3
Summary: py-data-api is a user-friendly client for AWS Postgres Aurora Serverless Data API
Home-page: https://github.com/Leafeanking/py-data-api-postgres
Author: Lofton Harmon
Author-email: lofton.harmon@gmail.com
License: UNKNOWN
Platform: UNKNOWN
Requires-Python: >=3.6.1
Requires-Dist: boto3 (==1.9.243)
Requires-Dist: SQLAlchemy (==1.3.7)
Requires-Dist: pydantic (==1.0b1)
Provides-Extra: all
Requires-Dist: setuptools-scm ; extra == 'all'
Requires-Dist: mkdocs ; extra == 'all'
Requires-Dist: mkdocs-material ; extra == 'all'
Requires-Dist: wheel ; extra == 'all'
Requires-Dist: twine ; extra == 'all'
Provides-Extra: docs
Requires-Dist: mkdocs ; extra == 'docs'
Requires-Dist: mkdocs-material ; extra == 'docs'
Provides-Extra: setup
Requires-Dist: setuptools-scm ; extra == 'setup'
Provides-Extra: wheel
Requires-Dist: wheel ; extra == 'wheel'
Requires-Dist: twine ; extra == 'wheel'
